moment_api/__init__.py
moment_api/api.py
moment_api-1.0.0.dist-info/LICENSE.txt
moment_api-1.0.0.dist-info/METADATA
moment_api-1.0.0.dist-info/WHEEL
moment_api-1.0.0.dist-info/top_level.txt
moment_api-1.0.0.dist-info/RECORD
