Metadata-Version: 2.1
Name: moment_api
Version: 1.0.0
Summary: Moment API: Доступ к LLAMA3 без нагрузки на ваше железо
Home-page: https://github.com/Stunfz
Author: Stung
Author-email: liko.03@bk.ru
Classifier: Programming Language :: Python :: 3
Classifier: License :: OSI Approved :: MIT License
Classifier: Operating System :: OS Independent
Requires-Python: >=3.6
License-File: LICENSE.txt
Requires-Dist: requests
